keras_attention/__init__.py
keras_attention/self_attention.py
keras_attention/settings.py
keras_attention-1.0.0.dist-info/LICENSE
keras_attention-1.0.0.dist-info/METADATA
keras_attention-1.0.0.dist-info/WHEEL
keras_attention-1.0.0.dist-info/top_level.txt
keras_attention-1.0.0.dist-info/RECORD
