Metadata-Version: 2.1
Name: keras-attention
Version: 1.0.0
Summary: Attention Mechanism Implementations for NLP via Keras
Home-page: https://github.com/Marcnuth/keras-attention
Author: Marcnuth
Author-email: hxianxian@gmail.com
License: Apache License 2.0
Platform: UNKNOWN
Classifier: Topic :: Scientific/Engineering :: Artificial Intelligence
Classifier: Topic :: Software Development :: Libraries
Classifier: Programming Language :: Python :: 3
Requires-Dist: keras
